Metadata-Version: 1.0
Name: GTAN-OC-PAC
Version: 0.1
Summary: POCKET
Home-page: UNKNOWN
Author: UNKNOWN
Author-email: Arkastar321@mail.ru
License: UNKNOWN
Platform: UNKNOWN
